{
  "schemaVersion": 1,
  "id": "modid",
  "version": "${version}",

  "name": "Mystical Arts",
  "description": "This is an example description! Tell everyone what your mod is about!",
  "authors": [
    "Maddymakesgames"
  ],
  "contact": {
    "homepage": "https://fabricmc.net/",
    "sources": "https://github.com/FabricMC/fabric-example-mod"
  },

  "license": "CC0-1.0",
  "icon": "assets/modid/icon.png",

  "environment": "*",
  "entrypoints": {
    "main": [
      "com.github.maddymakesgames.MysticalArts.MysticalArts"
    ],
    "client": [
      "com.github.maddymakesgames.MysticalArts.MysticalArtsClient"
    ]
  },
  "mixins": [
  ],

  "depends": {
    "fabricloader": ">=0.4.0",
    "fabric": "*"
  },
  "suggests": {
    "flamingo": "*"
  }
}
